odoo/addons/pos_default_payment_method/README.rst
odoo/addons/pos_default_payment_method/__init__.py
odoo/addons/pos_default_payment_method/__manifest__.py
odoo/addons/pos_default_payment_method/i18n/es.po
odoo/addons/pos_default_payment_method/i18n/fr.po
odoo/addons/pos_default_payment_method/i18n/hr_HR.po
odoo/addons/pos_default_payment_method/i18n/it.po
odoo/addons/pos_default_payment_method/i18n/nl_NL.po
odoo/addons/pos_default_payment_method/i18n/pos_default_payment_method.pot
odoo/addons/pos_default_payment_method/images/module_installed.png
odoo/addons/pos_default_payment_method/images/standard.png
odoo/addons/pos_default_payment_method/models/__init__.py
odoo/addons/pos_default_payment_method/models/pos_config.py
odoo/addons/pos_default_payment_method/static/description/icon.png
odoo/addons/pos_default_payment_method/static/src/js/pos_default_payment_method.js
odoo/addons/pos_default_payment_method/tests/__init__.py
odoo/addons/pos_default_payment_method/tests/test_constrain.py
odoo/addons/pos_default_payment_method/views/assets.xml
odoo/addons/pos_default_payment_method/views/pos_config_view.xml
odoo11_addon_pos_default_payment_method-11.0.1.0.1.dist-info/METADATA
odoo11_addon_pos_default_payment_method-11.0.1.0.1.dist-info/WHEEL
odoo11_addon_pos_default_payment_method-11.0.1.0.1.dist-info/top_level.txt
odoo11_addon_pos_default_payment_method-11.0.1.0.1.dist-info/RECORD
